newpool-0.1.0.dist-info/METADATA
newpool-0.1.0.dist-info/WHEEL
newpool-0.1.0.dist-info/entry_points.txt
newpool/__init__.py
newpool/newpool.py
newpool-0.1.0.dist-info/RECORD
