Metadata-Version: 2.1
Name: newpool
Version: 0.1.0
Summary: 更简单的使用异步协程和线程池
Author: jiaosenvip
Author-Email: jiaosenvip <jiaosenvip@163.com>
License: MIT
Project-URL: Homepage, https://github.com/jiaosenvip/newpool
Project-URL: Documentation, https://github.com/jiaosenvip/newpool/wiki
Requires-Python: >=3.11
Requires-Dist: rich
